typer_shell/__init__.py
typer_shell/samples.py
typer_shell/typer_shell.py
typer_shell/utils.py
typer_shell-1.0.3.dist-info/METADATA
typer_shell-1.0.3.dist-info/WHEEL
typer_shell-1.0.3.dist-info/licenses/LICENSE
typer_shell-1.0.3.dist-info/RECORD
