Metadata-Version: 2.4
Name: typer-shell
Version: 1.0.3
Summary: A shell for typer apps with autocompletion and history
Author-email: Fergus Fettes <fergusfettes@gmail.com>
License-File: LICENSE
Requires-Python: >=3.9.0
Requires-Dist: click-shell~=2.1
Requires-Dist: click>=8.1.0
Requires-Dist: pyyaml~=6.0
Requires-Dist: rich>=10.11.0
Requires-Dist: typer~=0.16.0
